{
    "properties": {
        "_id": {
            "bsonType": "objectId"
        },
        "actionLongDescription": {
            "bsonType": "string"
        },
        "actionSummary": {
            "bsonType": "string"
        },
        "explainerOppose": {
            "bsonType": "string"
        },
        "explainerSupport": {
            "bsonType": "string"
        },
        "fundingLongDescription": {
            "bsonType": "string"
        },
        "fundingSummary": {
            "bsonType": "string"
        },
        "jurisdiction": {
            "bsonType": "string"
        },
        "name": {
            "bsonType": "string"
        },
        "referenceLinks": {
            "bsonType": "string"
        },
        "relatedLegislation": {
            "bsonType": "string"
        }
    },
    "title": "Issue"
}
