{
    "properties": {
        "_id": {
            "bsonType": "objectId"
        },
        "citizenOf": {
            "bsonType": "array",
            "items": {
                "bsonType": "object",
                "properties": {
                    "jurisdictionID": {
                        "bsonType": "objectId"
                    },
                    "name": {
                        "bsonType": "string"
                    }
                }
            }
        },
        "dateOfBirth": {
            "bsonType": "date"
        },
        "email": {
            "bsonType": "string"
        },
        "gidImageBack": {
            "bsonType": "string"
        },
        "gidImageFront": {
            "bsonType": "string"
        },
        "gidNumber": {
            "bsonType": "string"
        },
        "nameFirst": {
            "bsonType": "string"
        },
        "nameLast": {
            "bsonType": "string"
        },
        "nameMiddle": {
            "bsonType": "string"
        },
        "phoneMobile": {
            "bsonType": "string"
        },
        "placeOfBirth": {
            "bsonType": "object",
            "properties": {
                "jurisdictionID": {
                    "bsonType": "objectId"
                },
                "name": {
                    "bsonType": "string"
                }
            }
        }
    },
    "title": "Citizen"
}
